setup.py
tools_x/__init__.py
tools_x.egg-info/PKG-INFO
tools_x.egg-info/SOURCES.txt
tools_x.egg-info/dependency_links.txt
tools_x.egg-info/not-zip-safe
tools_x.egg-info/top_level.txt