Metadata-Version: 1.0
Name: tools-x
Version: 0.1
Summary: Best of luck
Home-page: UNKNOWN
Author: fatal anonymous
Author-email: UNKNOWN
License: MIT
Platform: UNKNOWN
